[{"name":"Adelaide Hills","bounds":[[-35,138.6],[-34.9,138.9]]},{"name":"Bavaria","bounds":[[47.6,10.3],[50.6,13.6]]},{"name":"Costa Rica","bounds":[[8.3,-85.7],[11,-83]]},{"name":"Ecuador (Podocarpus National Park)","bounds":[[-4.5,-79.1],[-4,-78.8]]},{"name":"Macquarie Island","bounds":[[-55.1,157.9],[-54.1,159.9]]},{"name":"Philippines","bounds":[[6.6,118.7],[18.7,126.8]]},{"name":"Scotland (Loch Lomond)","bounds":[[56,-4.8],[56.5,-4.2]]},{"name":"Sea of Okhotsk","bounds":[[49.2,140.6],[59.3,156.6]]},{"name":"South Africa (Kruger National Park)","bounds":[[-25.4,31],[-22.4,32]]},{"name":"Spain (Doñana National Park)","bounds":[[36.8,-6.6],[37.2,-6.2]]},{"name":"Sri Lanka","bounds":[[5.8,79.4],[10,82.1]]},{"name":"USA (Death Valley)","bounds":[[35.6,-117.6],[37,-116.3]]},{"name":"Yukon Delta National Wildlife Refuge","bounds":[[59.7,-167.4],[63.5,-160.2]]}]
